njswpose/__init__.py
njswpose/njswpose.py
njswpose-0.1.5.dist-info/LICENSE
njswpose-0.1.5.dist-info/METADATA
njswpose-0.1.5.dist-info/WHEEL
njswpose-0.1.5.dist-info/top_level.txt
njswpose-0.1.5.dist-info/RECORD
