Metadata-Version: 2.1
Name: njswpose
Version: 0.1.5
Summary: Detection human body keypoints
Home-page: https://github.com/ddmm2020/njswpose
Author: ddmm
Author-email: 1126557295@qq.com
License: UNKNOWN
Platform: UNKNOWN
Classifier: Programming Language :: Python :: 3
Classifier: License :: OSI Approved :: MIT License
Classifier: Operating System :: OS Independent
